tfHuber.cp39-win_amd64.pyd
tfHuber-0.1.1.dist-info/LICENSE.txt
tfHuber-0.1.1.dist-info/METADATA
tfHuber-0.1.1.dist-info/WHEEL
tfHuber-0.1.1.dist-info/top_level.txt
tfHuber-0.1.1.dist-info/RECORD
