Metadata-Version: 2.1
Name: tfHuber
Version: 0.1.1
Summary: Python Package for tuning-free Huber Regression
Home-page: https://github.com/IV012/tfHuber
Author: Yifan Dai & Qiang Sun
Author-email: yifandai@yeah.net, qsun.ustc@gmail.com
License: GPL (ver 3)
Platform: UNKNOWN
Requires-Python: >=3.5
